odoo/addons/account_analytic_distribution_model_recalculate/README.rst
odoo/addons/account_analytic_distribution_model_recalculate/__init__.py
odoo/addons/account_analytic_distribution_model_recalculate/__manifest__.py
odoo/addons/account_analytic_distribution_model_recalculate/i18n/account_analytic_distribution_model_recalculate.pot
odoo/addons/account_analytic_distribution_model_recalculate/i18n/ca.po
odoo/addons/account_analytic_distribution_model_recalculate/i18n/es.po
odoo/addons/account_analytic_distribution_model_recalculate/i18n/it.po
odoo/addons/account_analytic_distribution_model_recalculate/models/__init__.py
odoo/addons/account_analytic_distribution_model_recalculate/models/account_analytic_distribution_model.py
odoo/addons/account_analytic_distribution_model_recalculate/models/account_move_line.py
odoo/addons/account_analytic_distribution_model_recalculate/readme/CONTRIBUTORS.md
odoo/addons/account_analytic_distribution_model_recalculate/readme/DESCRIPTION.md
odoo/addons/account_analytic_distribution_model_recalculate/readme/USAGE.md
odoo/addons/account_analytic_distribution_model_recalculate/static/description/icon.png
odoo/addons/account_analytic_distribution_model_recalculate/static/description/index.html
odoo/addons/account_analytic_distribution_model_recalculate/tests/__init__.py
odoo/addons/account_analytic_distribution_model_recalculate/tests/test_account_analytic_distribution_model.py
odoo/addons/account_analytic_distribution_model_recalculate/views/account_analytic_distribution_model.xml
odoo/addons/account_analytic_distribution_model_recalculate/views/account_move_line.xml
odoo_addon_account_analytic_distribution_model_recalculate-17.0.1.0.1.2.dist-info/METADATA
odoo_addon_account_analytic_distribution_model_recalculate-17.0.1.0.1.2.dist-info/WHEEL
odoo_addon_account_analytic_distribution_model_recalculate-17.0.1.0.1.2.dist-info/top_level.txt
odoo_addon_account_analytic_distribution_model_recalculate-17.0.1.0.1.2.dist-info/RECORD
